{
    "badge_id": "B03125",
    "name": "Python Certification",
    "issuer": "Coursera",
    "description": "Python Certification badge issued by Coursera",
    "criteria": "Passing all module assessments",
    "alignment": "Academic Alignment",
    "employmentOutcome": "Eligible for Data Analyst roles",
    "skillsValidated": "['Machine Learning', 'DevOps', 'Data Analysis']",
    "competency": "['Problem Solving', 'Deep Learning', 'Cloud Computing']",
    "learningOpportunity": "Intro to Machine Learning",
    "related_badges": "[]"
}