{
    "badge_id": "B06539",
    "name": "Deep Learning Master",
    "issuer": "Udacity",
    "description": "Deep Learning Master badge issued by Udacity",
    "criteria": "Completion of 40 hours of lectures and project submission",
    "alignment": "Professional Alignment",
    "employmentOutcome": "Eligible for Cloud Architect positions",
    "skillsValidated": "['Deep Learning', 'SQL']",
    "competency": "['Teamwork']",
    "learningOpportunity": "Cloud Computing Course",
    "related_badges": "[]"
}