{
    "badge_id": "B07675",
    "name": "Cloud Computing Guru",
    "issuer": "Coursera",
    "description": "Cloud Computing Guru badge issued by Coursera",
    "criteria": "Passing all module assessments",
    "alignment": "Academic Alignment",
    "employmentOutcome": "Eligible for Data Analyst roles",
    "skillsValidated": "['Cybersecurity', 'Deep Learning']",
    "competency": "['Problem Solving', 'Teamwork']",
    "learningOpportunity": "Intro to Machine Learning",
    "related_badges": "[]"
}