{
    "badge_id": "B07766",
    "name": "Data Science Expert",
    "issuer": "edX",
    "description": "Data Science Expert badge issued by edX",
    "criteria": "Passing all module assessments",
    "alignment": "Industry Standard Alignment",
    "employmentOutcome": "Eligible for Data Analyst roles",
    "skillsValidated": "['Cloud Computing', 'Machine Learning']",
    "competency": "['DevOps', 'Analytical Skills']",
    "learningOpportunity": "Big Data Analysis Program",
    "related_badges": "['B06845', 'B04851']"
}