{
    "badge_id": "B08669",
    "name": "DevOps Engineer",
    "issuer": "edX",
    "description": "DevOps Engineer badge issued by edX",
    "criteria": "Completion of 40 hours of lectures and project submission",
    "alignment": "Professional Alignment",
    "employmentOutcome": "Eligible for Cloud Architect positions",
    "skillsValidated": "['Deep Learning', 'Machine Learning', 'Data Analysis']",
    "competency": "['SQL', 'Machine Learning', 'UI/UX']",
    "learningOpportunity": "Data Science Bootcamp",
    "related_badges": "['B09823']"
}