{
    "badge_id": "B02279",
    "name": "Python Certification",
    "issuer": "edX",
    "description": "Python Certification badge issued by edX",
    "criteria": "Completion of hands-on project and final evaluation",
    "alignment": "Industry Standard Alignment",
    "employmentOutcome": "Eligible for Data Analyst roles",
    "skillsValidated": "['UI/UX', 'Cybersecurity']",
    "competency": "['Problem Solving']",
    "learningOpportunity": "Intro to Machine Learning",
    "related_badges": "[]"
}