{
    "badge_id": "B01534",
    "name": "Cybersecurity Professional",
    "issuer": "Udacity",
    "description": "Cybersecurity Professional badge issued by Udacity",
    "criteria": "Passing all module assessments",
    "alignment": "Academic Alignment",
    "employmentOutcome": "Eligible for Software Engineer roles",
    "skillsValidated": "['Python', 'Cloud Computing']",
    "competency": "['Teamwork']",
    "learningOpportunity": "Data Science Bootcamp",
    "related_badges": "['B06927', 'B05948']"
}