{
    "badge_id": "B06391",
    "name": "Data Science Expert",
    "issuer": "Udacity",
    "description": "Data Science Expert badge issued by Udacity",
    "criteria": "Completion of 40 hours of lectures and project submission",
    "alignment": "Academic Alignment",
    "employmentOutcome": "Eligible for Machine Learning Engineer positions",
    "skillsValidated": "['Cybersecurity', 'SQL', 'DevOps']",
    "competency": "['Leadership', 'DevOps']",
    "learningOpportunity": "Data Science Bootcamp",
    "related_badges": "['B06544']"
}