{
    "badge_id": "B03014",
    "name": "AI Specialist",
    "issuer": "edX",
    "description": "AI Specialist badge issued by edX",
    "criteria": "Completion of hands-on project and final evaluation",
    "alignment": "Industry Standard Alignment",
    "employmentOutcome": "Eligible for Machine Learning Engineer positions",
    "skillsValidated": "['Deep Learning', 'Cybersecurity']",
    "competency": "['DevOps', 'SQL', 'UI/UX']",
    "learningOpportunity": "Big Data Analysis Program",
    "related_badges": "['B03223']"
}