{
    "badge_id": "B03846",
    "name": "DevOps Engineer",
    "issuer": "Coursera",
    "description": "DevOps Engineer badge issued by Coursera",
    "criteria": "Completion of 40 hours of lectures and project submission",
    "alignment": "Professional Alignment",
    "employmentOutcome": "Eligible for Machine Learning Engineer positions",
    "skillsValidated": "['Deep Learning', 'Machine Learning', 'Python']",
    "competency": "['Data Analysis', 'Cybersecurity']",
    "learningOpportunity": "Big Data Analysis Program",
    "related_badges": "['B09051', 'B03396']"
}