{
    "badge_id": "B09309",
    "name": "Data Science Expert",
    "issuer": "Google",
    "description": "Data Science Expert badge issued by Google",
    "criteria": "Completion of 40 hours of lectures and project submission",
    "alignment": "Academic Alignment",
    "employmentOutcome": "Eligible for Cloud Architect positions",
    "skillsValidated": "['Cybersecurity', 'SQL']",
    "competency": "['Cloud Computing', 'Cybersecurity', 'Data Analysis']",
    "learningOpportunity": "Big Data Analysis Program",
    "related_badges": "[]"
}