{
    "badge_id": "B05206",
    "name": "DevOps Engineer",
    "issuer": "Udacity",
    "description": "DevOps Engineer badge issued by Udacity",
    "criteria": "Passing all module assessments",
    "alignment": "Industry Standard Alignment",
    "employmentOutcome": "Eligible for Cloud Architect positions",
    "skillsValidated": "['Data Analysis']",
    "competency": "['Data Analysis', 'Deep Learning', 'Python']",
    "learningOpportunity": "Intro to Machine Learning",
    "related_badges": "['B07708']"
}