{
    "badge_id": "B06566",
    "name": "Data Science Expert",
    "issuer": "Google",
    "description": "Data Science Expert badge issued by Google",
    "criteria": "Passing all module assessments",
    "alignment": "Academic Alignment",
    "employmentOutcome": "Eligible for Software Engineer roles",
    "skillsValidated": "['Cybersecurity', 'SQL']",
    "competency": "['Analytical Skills', 'Python']",
    "learningOpportunity": "Data Science Bootcamp",
    "related_badges": "['B02034', 'B04671']"
}