{
    "badge_id": "B09726",
    "name": "Data Science Expert",
    "issuer": "Google",
    "description": "Data Science Expert badge issued by Google",
    "criteria": "Passing all module assessments",
    "alignment": "Professional Alignment",
    "employmentOutcome": "Eligible for Software Engineer roles",
    "skillsValidated": "['Machine Learning', 'Python']",
    "competency": "['Machine Learning', 'Python', 'Cybersecurity']",
    "learningOpportunity": "Intro to Machine Learning",
    "related_badges": "['B03199', 'B08118']"
}