{
    "badge_id": "B06451",
    "name": "Big Data Analyst",
    "issuer": "Coursera",
    "description": "Big Data Analyst badge issued by Coursera",
    "criteria": "Completion of 40 hours of lectures and project submission",
    "alignment": "Professional Alignment",
    "employmentOutcome": "Eligible for Cloud Architect positions",
    "skillsValidated": "['Machine Learning', 'Cybersecurity']",
    "competency": "['UI/UX']",
    "learningOpportunity": "AI Professional Course",
    "related_badges": "[]"
}