{
    "badge_id": "B09272",
    "name": "Data Science Expert",
    "issuer": "Google",
    "description": "Data Science Expert badge issued by Google",
    "criteria": "Completion of 40 hours of lectures and project submission",
    "alignment": "Academic Alignment",
    "employmentOutcome": "Eligible for Machine Learning Engineer positions",
    "skillsValidated": "['UI/UX', 'Deep Learning']",
    "competency": "['SQL']",
    "learningOpportunity": "Intro to Machine Learning",
    "related_badges": "[]"
}