{
    "badge_id": "B07121",
    "name": "Cybersecurity Professional",
    "issuer": "Google",
    "description": "Cybersecurity Professional badge issued by Google",
    "criteria": "Completion of hands-on project and final evaluation",
    "alignment": "Professional Alignment",
    "employmentOutcome": "Eligible for Data Analyst roles",
    "skillsValidated": "['Deep Learning']",
    "competency": "['Python', 'Machine Learning', 'Cloud Computing']",
    "learningOpportunity": "Cloud Computing Course",
    "related_badges": "[]"
}