{
    "badge_id": "B08083",
    "name": "Cybersecurity Professional",
    "issuer": "Coursera",
    "description": "Cybersecurity Professional badge issued by Coursera",
    "criteria": "Passing all module assessments",
    "alignment": "Academic Alignment",
    "employmentOutcome": "Eligible for Cloud Architect positions",
    "skillsValidated": "['Cybersecurity', 'UI/UX', 'Machine Learning']",
    "competency": "['SQL']",
    "learningOpportunity": "Data Science Bootcamp",
    "related_badges": "[]"
}