{
    "badge_id": "B03045",
    "name": "Machine Learning Pro",
    "issuer": "Udacity",
    "description": "Machine Learning Pro badge issued by Udacity",
    "criteria": "Completion of hands-on project and final evaluation",
    "alignment": "Academic Alignment",
    "employmentOutcome": "Eligible for Machine Learning Engineer positions",
    "skillsValidated": "['Cybersecurity', 'Cloud Computing']",
    "competency": "['Problem Solving']",
    "learningOpportunity": "AI Professional Course",
    "related_badges": "['B00402']"
}