{
    "badge_id": "B07628",
    "name": "Machine Learning Pro",
    "issuer": "Google",
    "description": "Machine Learning Pro badge issued by Google",
    "criteria": "Completion of hands-on project and final evaluation",
    "alignment": "Professional Alignment",
    "employmentOutcome": "Eligible for Data Analyst roles",
    "skillsValidated": "['Python', 'Cloud Computing']",
    "competency": "['Teamwork', 'Creativity', 'Analytical Skills']",
    "learningOpportunity": "Data Science Bootcamp",
    "related_badges": "[]"
}