{
    "badge_id": "B00872",
    "name": "Big Data Analyst",
    "issuer": "Coursera",
    "description": "Big Data Analyst badge issued by Coursera",
    "criteria": "Completion of hands-on project and final evaluation",
    "alignment": "Industry Standard Alignment",
    "employmentOutcome": "Eligible for Software Engineer roles",
    "skillsValidated": "['Python']",
    "competency": "['Analytical Skills', 'Cybersecurity']",
    "learningOpportunity": "Data Science Bootcamp",
    "related_badges": "[]"
}