{
    "badge_id": "B00624",
    "name": "Deep Learning Master",
    "issuer": "Udacity",
    "description": "Deep Learning Master badge issued by Udacity",
    "criteria": "Completion of hands-on project and final evaluation",
    "alignment": "Academic Alignment",
    "employmentOutcome": "Eligible for Software Engineer roles",
    "skillsValidated": "['Deep Learning', 'DevOps', 'Data Analysis']",
    "competency": "['Python', 'SQL']",
    "learningOpportunity": "Intro to Machine Learning",
    "related_badges": "[]"
}