{
    "badge_id": "B00904",
    "name": "AI Specialist",
    "issuer": "Udacity",
    "description": "AI Specialist badge issued by Udacity",
    "criteria": "Completion of hands-on project and final evaluation",
    "alignment": "Academic Alignment",
    "employmentOutcome": "Eligible for Data Analyst roles",
    "skillsValidated": "['Deep Learning', 'Data Analysis', 'Cybersecurity']",
    "competency": "['SQL', 'Creativity', 'Deep Learning']",
    "learningOpportunity": "Big Data Analysis Program",
    "related_badges": "[]"
}