{
    "user_id": "U03956",
    "name": "Susan Hodges",
    "email": "kristy56@example.net",
    "goal": "Become a Machine Learning Researcher",
    "skills": "['Machine Learning', 'UI/UX', 'Cloud Computing', 'Data Analysis']",
    "competency_level": "Intermediate",
    "acquired_badges": "['B09264', 'B06409', 'B01344']",
    "learning_history": "Completed the 'Data Science Expert' course at edX",
    "employment_history": "Worked at Hughes LLC for 3 years",
    "education_level": "High School",
    "engagement_metrics": "Highly Active",
    "recommendation_history": "['B02878', 'B07330', 'B02477', 'B04636']"
}