{
    "user_id": "U08399",
    "name": "Kathryn Hall",
    "email": "nduran@example.net",
    "goal": "Become a Data Scientist",
    "skills": "['Machine Learning', 'Data Analysis']",
    "competency_level": "Advanced",
    "acquired_badges": "[]",
    "learning_history": "Completed the 'Big Data Analyst' course at Google",
    "employment_history": "Worked at Anderson, Little and Pope for 3 years",
    "education_level": "Bachelor's Degree",
    "engagement_metrics": "Moderate",
    "recommendation_history": "['B03407']"
}