{
    "user_id": "U03713",
    "name": "Kevin Petersen",
    "email": "angelicapayne@example.org",
    "goal": "Become a Cloud Engineer",
    "skills": "['Cloud Computing', 'Data Analysis']",
    "competency_level": "Intermediate",
    "acquired_badges": "['B06527']",
    "learning_history": "Completed the 'Big Data Analyst' course at IBM",
    "employment_history": "Worked at Meyers, Yates and Burton for 1 years",
    "education_level": "PhD",
    "engagement_metrics": "Moderate",
    "recommendation_history": "['B05186', 'B03180', 'B00461', 'B01643']"
}