{
    "user_id": "U01561",
    "name": "Valerie Cooper",
    "email": "xwilliams@example.org",
    "goal": "Become a Machine Learning Researcher",
    "skills": "['Python', 'UI/UX', 'Cloud Computing', 'Data Analysis']",
    "competency_level": "Beginner",
    "acquired_badges": "['B04469', 'B06218', 'B07706']",
    "learning_history": "Completed the 'Cybersecurity Professional' course at edX",
    "employment_history": "Worked at Evans, Sanchez and Hamilton for 4 years",
    "education_level": "Master's Degree",
    "engagement_metrics": "Moderate",
    "recommendation_history": "['B04981', 'B04723', 'B08247']"
}