{
    "user_id": "U01693",
    "name": "Kyle Collins",
    "email": "garciatammie@example.net",
    "goal": "Become a Software Engineer",
    "skills": "['UI/UX', 'SQL']",
    "competency_level": "Advanced",
    "acquired_badges": "['B07626', 'B09951', 'B07573', 'B02223', 'B02600']",
    "learning_history": "Completed the 'AI Specialist' course at Google",
    "employment_history": "Worked at Stein-Brooks for 1 years",
    "education_level": "Bachelor's Degree",
    "engagement_metrics": "Moderate",
    "recommendation_history": "[]"
}