{
    "user_id": "U08703",
    "name": "Grant Perez",
    "email": "michelle94@example.com",
    "goal": "Become a Cloud Engineer",
    "skills": "['Cybersecurity']",
    "competency_level": "Beginner",
    "acquired_badges": "['B03583', 'B00782', 'B03418', 'B01714', 'B07809']",
    "learning_history": "Completed the 'Cloud Computing Guru' course at edX",
    "employment_history": "Worked at Gates LLC for 4 years",
    "education_level": "Bachelor's Degree",
    "engagement_metrics": "Highly Active",
    "recommendation_history": "['B06724']"
}