{
    "user_id": "U09530",
    "name": "Spencer Hall DDS",
    "email": "susan83@example.org",
    "goal": "Become a Cloud Engineer",
    "skills": "['UI/UX', 'Python']",
    "competency_level": "Beginner",
    "acquired_badges": "[]",
    "learning_history": "Completed the 'Deep Learning Master' course at Google",
    "employment_history": "Worked at Jones-Martin for 4 years",
    "education_level": "Master's Degree",
    "engagement_metrics": "Low",
    "recommendation_history": "['B02712', 'B09923', 'B05072']"
}