{
    "user_id": "U09561",
    "name": "Trevor Mayo",
    "email": "evansralph@example.org",
    "goal": "Become a Cloud Engineer",
    "skills": "['Deep Learning', 'DevOps', 'Data Analysis', 'Cloud Computing']",
    "competency_level": "Beginner",
    "acquired_badges": "[]",
    "learning_history": "Completed the 'Data Science Expert' course at Udacity",
    "employment_history": "Worked at Callahan LLC for 5 years",
    "education_level": "Bachelor's Degree",
    "engagement_metrics": "Low",
    "recommendation_history": "['B08849']"
}