{
    "user_id": "U01448",
    "name": "Reginald Hudson",
    "email": "chumphrey@example.net",
    "goal": "Become an AI Expert",
    "skills": "['Python', 'Cloud Computing']",
    "competency_level": "Intermediate",
    "acquired_badges": "['B03853', 'B09248', 'B02729']",
    "learning_history": "Completed the 'Big Data Analyst' course at edX",
    "employment_history": "Worked at Lewis-Castaneda for 5 years",
    "education_level": "High School",
    "engagement_metrics": "Highly Active",
    "recommendation_history": "['B09836']"
}