{
    "user_id": "U08845",
    "name": "Cory Day",
    "email": "jeff04@example.com",
    "goal": "Become an AI Expert",
    "skills": "['SQL', 'Machine Learning', 'Data Analysis', 'UI/UX']",
    "competency_level": "Intermediate",
    "acquired_badges": "['B04477', 'B03537']",
    "learning_history": "Completed the 'Big Data Analyst' course at Google",
    "employment_history": "Worked at Roberts-Weaver for 2 years",
    "education_level": "High School",
    "engagement_metrics": "Moderate",
    "recommendation_history": "['B08273', 'B06051', 'B00419']"
}