{
    "user_id": "U00615",
    "name": "Taylor White",
    "email": "jeffreyanderson@example.org",
    "goal": "Become a Cloud Engineer",
    "skills": "['SQL']",
    "competency_level": "Intermediate",
    "acquired_badges": "['B03043', 'B03703', 'B04433']",
    "learning_history": "Completed the 'Deep Learning Master' course at Udacity",
    "employment_history": "Worked at Sanders PLC for 5 years",
    "education_level": "Master's Degree",
    "engagement_metrics": "Moderate",
    "recommendation_history": "['B09620']"
}