{
    "user_id": "U08750",
    "name": "Julia Roman",
    "email": "hailey85@example.net",
    "goal": "Become a Software Engineer",
    "skills": "['Cloud Computing', 'Deep Learning']",
    "competency_level": "Intermediate",
    "acquired_badges": "['B03265', 'B09910']",
    "learning_history": "Completed the 'Big Data Analyst' course at Coursera",
    "employment_history": "Worked at Webb, Cox and Vega for 5 years",
    "education_level": "Master's Degree",
    "engagement_metrics": "Highly Active",
    "recommendation_history": "[]"
}